{
	"_id": "VKpXZNF9sOweyGZc",
	"_key": "!items!VKpXZNF9sOweyGZc",
	"name": "A Mighty Rampart",
	"type": "move",
	"system": {
		"playbook": "The Judge",
		"moveType": "playbook",
		"description": "When you **_hold Readiness (from Defend)_**, you cannot be forced from your position. Also, you can spend 1 Readiness to completely ignore the effects/damage of an attack that you suffer. (Replaces Bulwark.)",
		"requirement": {
			"level": 6,
			"moves": [
				"Bulwark"
			]
		},
		"slug": "a-mighty-rampart"
	},
	"folder": "jISe56pNVdmHJLgu"
}
