{
	"_id": "PQASUEEI8FOXHgfF",
	"_key": "!actors!PQASUEEI8FOXHgfF",
	"name": "Log spirit",
	"type": "npc",
	"img": "systems/stonetop/assets/content/wonders/markers/marker-swirl.png",
	"system": {
		"slug": "log-spirit",
		"reference": "spirits-of-the-wild",
		"tagList": {
			"selected": [
				"Solitary",
				"spirit",
				"sickly",
				"cheerful",
				"giving"
			],
			"options": [],
			"multi": true,
			"allowCustom": true
		},
		"hp": {
			"value": 0,
			"max": 0
		},
		"armor": "",
		"damage": "",
		"specialQuality": "",
		"instinct": {
			"selected": [
				"to not mind, really"
			],
			"options": [],
			"multi": false,
			"allowCustom": true
		},
		"moves": "",
		"description": "Source: @UUID[Compendium.stonetop.wider-world-and-other-wonders.JournalEntry.HOWpYxmR8Q44qS3E]{Spirits of the wild} (Book p.356-371)",
		"notes": "Ho-hum, it’s okay; falls apart under serious pressure."
	},
	"ownership": {
		"default": 0
	},
	"flags": {},
	"folder": "bZjX6JvUtGDAtnSK"
}
